AiKaifazheDeDockerShijian/README.md
AiKaifazheDeDockerShijian/__init__.py
AiKaifazheDeDockerShijian/__main__.py
AiKaifazheDeDockerShijian/file.pdf
AiKaifazheDeDockerShijian/index.html
ai_kaifazhe_de_docker_shijian-2024.3.5.0.dist-info/METADATA
ai_kaifazhe_de_docker_shijian-2024.3.5.0.dist-info/WHEEL
ai_kaifazhe_de_docker_shijian-2024.3.5.0.dist-info/entry_points.txt
ai_kaifazhe_de_docker_shijian-2024.3.5.0.dist-info/top_level.txt
ai_kaifazhe_de_docker_shijian-2024.3.5.0.dist-info/RECORD
